tesseract_client/__init__.py
tesseract_client/api_manager.py
tesseract_client/chunk.py
tesseract_client/config.py
tesseract_client/db_manager.py
tesseract_client/file.py
tesseract_client/main.py
tesseract_client/monitoring.py
tesseract_client/services.py
tesseract_client/cli/__init__.py
tesseract_client/cli/config.py
tesseract_client/cli/login.py
tesseract_client/cli/logout.py
tesseract_client/cli/pull.py
tesseract_client/cli/run.py
tesseract_client/cli/signup.py
tesseract_client-0.0.8.dist-info/METADATA
tesseract_client-0.0.8.dist-info/WHEEL
tesseract_client-0.0.8.dist-info/entry_points.txt
tesseract_client-0.0.8.dist-info/licenses/LICENSE
tesseract_client-0.0.8.dist-info/RECORD
