Metadata-Version: 2.1
Name: tesseract_client
Version: 0.0.8
Summary: Client for Tesseract API
Project-URL: Homepage, https://gitlab-stud.elka.pw.edu.pl/mstelmak/zprp-cloud-storage
Project-URL: Issues, https://gitlab-stud.elka.pw.edu.pl/mstelmak/zprp-cloud-storage/issues
License-File: LICENSE
Classifier: License :: OSI Approved :: MIT License
Classifier: Operating System :: OS Independent
Classifier: Programming Language :: Python :: 3
Requires-Python: >=3.10
Requires-Dist: annotated-types==0.6.0
Requires-Dist: attrs==23.1.0
Requires-Dist: cachetools==5.3.2
Requires-Dist: certifi==2023.7.22
Requires-Dist: cffi==1.16.0
Requires-Dist: chardet==5.2.0
Requires-Dist: charset-normalizer==3.3.2
Requires-Dist: click==8.1.7
Requires-Dist: colorama==0.4.6
Requires-Dist: cryptography==41.0.7
Requires-Dist: distlib==0.3.8
Requires-Dist: exceptiongroup==1.2.0
Requires-Dist: filelock==3.13.1
Requires-Dist: flake8==6.1.0
Requires-Dist: ghp-import==2.1.0
Requires-Dist: hypothesis==6.92.0
Requires-Dist: idna==3.4
Requires-Dist: importlib-metadata==7.0.0
Requires-Dist: iniconfig==2.0.0
Requires-Dist: jaraco-classes==3.3.0
Requires-Dist: jeepney==0.8.0
Requires-Dist: jinja2==3.1.2
Requires-Dist: keyring==24.3.0
Requires-Dist: loguru==0.7.2
Requires-Dist: markdown==3.5.1
Requires-Dist: markupsafe==2.1.3
Requires-Dist: mccabe==0.7.0
Requires-Dist: mergedeep==1.3.4
Requires-Dist: mkdocs==1.5.3
Requires-Dist: more-itertools==10.1.0
Requires-Dist: packaging==23.2
Requires-Dist: pathspec==0.12.1
Requires-Dist: platformdirs==4.1.0
Requires-Dist: pluggy==1.3.0
Requires-Dist: pycodestyle==2.11.1
Requires-Dist: pycparser==2.21
Requires-Dist: pyflakes==3.1.0
Requires-Dist: pyproject-api==1.6.1
Requires-Dist: pytest-mock==3.12.0
Requires-Dist: pytest==7.4.3
Requires-Dist: python-dateutil==2.8.2
Requires-Dist: python-dotenv==1.0.0
Requires-Dist: pyyaml-env-tag==0.1
Requires-Dist: pyyaml==6.0.1
Requires-Dist: requests==2.31.0
Requires-Dist: responses==0.24.1
Requires-Dist: secretstorage==3.3.3
Requires-Dist: six==1.16.0
Requires-Dist: sortedcontainers==2.4.0
Requires-Dist: tomli==2.0.1
Requires-Dist: tox==4.11.4
Requires-Dist: typing-extensions==4.8.0
Requires-Dist: urllib3==2.0.7
Requires-Dist: virtualenv==20.25.0
Requires-Dist: watchdog==3.0.0
Requires-Dist: zipp==3.17.0
